CHANGES.txt
MANIFEST.in
README-shorttests.txt
README.txt
bootstrap.py
buildout.cfg
setup.py
tests.py
upgrading.txt
dolmenproject/__init__.py
dolmenproject/main.py
dolmenproject/templates.py
dolmenproject.egg-info/PKG-INFO
dolmenproject.egg-info/SOURCES.txt
dolmenproject.egg-info/dependency_links.txt
dolmenproject.egg-info/entry_points.txt
dolmenproject.egg-info/not-zip-safe
dolmenproject.egg-info/requires.txt
dolmenproject.egg-info/top_level.txt
dolmenproject/template/sources.cfg
dolmenproject/template/src/+package+/app.py_tmpl
dolmenproject/template/src/+package+/configure.zcml_tmpl