Metadata-Version: 1.0
Name: dolmenproject
Version: 1.0a3
Summary: Script that creates a Dolmen project directory, installs Grok, the Grok Toolkit and the Zope Toolkit and sets up a complete skeleton for a new Dolmen application.
Home-page: http://www.dolmen-project.org
Author: Dolmen Team
Author-email: vincent.fretin@gmail.com
License: ZPL
Platform: UNKNOWN
